pytest_static/__init__.py
pytest_static/__main__.py
pytest_static/custom_typing.py
pytest_static/parametric.py
pytest_static/plugin.py
pytest_static/py.typed
pytest_static/type_handler.py
pytest_static/type_sets.py
pytest_static/util.py
pytest_static-1.1.1.dist-info/entry_points.txt
pytest_static-1.1.1.dist-info/LICENSE
pytest_static-1.1.1.dist-info/METADATA
pytest_static-1.1.1.dist-info/WHEEL
pytest_static-1.1.1.dist-info/RECORD
