Metadata-Version: 2.3
Name: pytest-static
Version: 1.1.1
Summary: pytest-static
License: MIT
Author: Kyle Oliver
Author-email: 56kyleoliver@gmail.com
Requires-Python: >=3.9,<4.0
Classifier: Development Status :: 3 - Alpha
Classifier: Framework :: Pytest
Classifier: License :: OSI Approved :: MIT License
Classifier: Operating System :: OS Independent
Classifier: Programming Language :: Python :: 3
Classifier: Programming Language :: Python :: 3.9
Classifier: Programming Language :: Python :: 3.10
Classifier: Programming Language :: Python :: 3.11
Classifier: Programming Language :: Python :: 3.12
Classifier: Programming Language :: Python :: 3.13
Classifier: Topic :: Software Development :: Testing
Requires-Dist: click (>=8.0.1)
Requires-Dist: loguru (>=0.7.2,<0.8.0)
Requires-Dist: platformdirs (>=4.2.2,<5.0.0)
Requires-Dist: pytest (>=7.4.3,<8.0.0)
Requires-Dist: typing-extensions (>=4.9.0,<5.0.0)
Project-URL: Changelog, https://github.com/56kyle/pytest-static/releases
Project-URL: Documentation, https://pytest-static.readthedocs.io
Project-URL: Homepage, https://github.com/56kyle/pytest-static
Project-URL: Repository, https://github.com/56kyle/pytest-static
